{
  "projectId": "focal-solution-32t1j",
  "appId": "1:560857211389:web:6a209186bc52f93f3e3994",
  "apiKey": "AIzaSyB_zIYHHpqdi9xcnzoeoWHk2KLQEZ872o4",
  "authDomain": "focal-solution-32t1j.firebaseapp.com",
  "firestoreDatabaseId": "ai-studio-4a326076-3c7b-4a1d-97e7-bfc0ba917580",
  "storageBucket": "focal-solution-32t1j.firebasestorage.app",
  "messagingSenderId": "560857211389",
  "measurementId": "",
  "oAuthClientId": "560857211389-hvsdheljd2pi0g70utmd0buldv33uoqe.apps.googleusercontent.com"
}